{
    "resourceType": "OperationOutcome",
    "issue": [
      {
        "severity": "error",
        "code": "structure",
        "details": {
          "coding": [
            {
              "system": "https://fhir.nhs.uk/R4/CodeSystem/Spine-ErrorOrWarningCode",
              "version": "1",
              "code": "INVALID_UPDATE",
              "display": "Update is invalid"
            }
          ]
        },
        "diagnostics": "Invalid update with error - Update unsupported for resource - 'pets'"
      }
    ]
  }